Metadata-Version: 1.0
Name: collective.recipe.mxbase
Version: 0.1
Summary: A buildout recipe to install eGenix mx.base (mx.DateTime, mx.TextTools...)
Home-page: http://svn.plone.org/svn/collective/buildout/collective.recipe.mxbase
Author: Jean-Francois Roche
Author-email: jfroche@affinitic.be
License: GPL
Keywords: build mx.Base
Platform: UNKNOWN
Classifier: Development Status :: 3 - Alpha
Classifier: Environment :: Plugins
Classifier: Intended Audience :: System Administrators
Classifier: Framework :: Buildout
Classifier: License :: OSI Approved :: GNU General Public License (GPL)
Classifier: Programming Language :: Python
Classifier: Topic :: System :: Installation/Setup
Classifier: Topic :: Software Development :: Libraries :: Python Modules
